printobject/__init__.py
printobject/prettyprinter.py
printobject/demos.py
printobject-0.1.6.dist-info/WHEEL
printobject-0.1.6.dist-info/pydist.json
printobject-0.1.6.dist-info/RECORD
printobject-0.1.6.dist-info/DESCRIPTION.rst
printobject-0.1.6.dist-info/METADATA
printobject-0.1.6.dist-info/top_level.txt
